odoo/addons/account_asset_stock_move/README.rst
odoo/addons/account_asset_stock_move/__init__.py
odoo/addons/account_asset_stock_move/__manifest__.py
odoo/addons/account_asset_stock_move/i18n/account_asset_stock_move.pot
odoo/addons/account_asset_stock_move/i18n/es.po
odoo/addons/account_asset_stock_move/i18n/it.po
odoo/addons/account_asset_stock_move/models/__init__.py
odoo/addons/account_asset_stock_move/models/stock_move.py
odoo/addons/account_asset_stock_move/models/stock_picking.py
odoo/addons/account_asset_stock_move/readme/CONFIGURE.rst
odoo/addons/account_asset_stock_move/readme/CONTRIBUTORS.rst
odoo/addons/account_asset_stock_move/readme/DESCRIPTION.rst
odoo/addons/account_asset_stock_move/readme/USAGE.rst
odoo/addons/account_asset_stock_move/static/description/icon.png
odoo/addons/account_asset_stock_move/static/description/index.html
odoo/addons/account_asset_stock_move/tests/__init__.py
odoo/addons/account_asset_stock_move/tests/test_account_asset_stock_move.py
odoo/addons/account_asset_stock_move/views/stock.xml
odoo14_addon_account_asset_stock_move-14.0.1.0.1.dev6.dist-info/METADATA
odoo14_addon_account_asset_stock_move-14.0.1.0.1.dev6.dist-info/WHEEL
odoo14_addon_account_asset_stock_move-14.0.1.0.1.dev6.dist-info/top_level.txt
odoo14_addon_account_asset_stock_move-14.0.1.0.1.dev6.dist-info/RECORD
